{
    "os": "Linux-5.4.0-177-generic-x86_64-with-glibc2.31",
    "python": "3.11.7",
    "heartbeatAt": "2024-04-22T10:02:58.499286",
    "startedAt": "2024-04-22T10:02:57.723670",
    "docker": null,
    "cuda": null,
    "args": [],
    "state": "running",
    "program": "/home/bimokhtari1/Documents/Image-Clustering-Based-on-Node-Edge-Duality-Message-Passing-Using-Graph-Attention-Networks/src/visualize.py",
    "codePathLocal": "visualize.py",
    "codePath": "src/visualize.py",
    "git": {
        "remote": "https://github.com/Billal-MOKHTARI/Image-Clustering-Based-on-Node-Edge-Duality-Message-Passing-Using-Graph-Attention-Networks.git",
        "commit": "2f0315824876ee34570d23a13e5db16804421b09"
    },
    "email": "billal.mokhtari@etu.uca.fr",
    "root": "/home/bimokhtari1/Documents/Image-Clustering-Based-on-Node-Edge-Duality-Message-Passing-Using-Graph-Attention-Networks",
    "host": "f205pc13",
    "username": "bimokhtari1",
    "executable": "/home/bimokhtari1/anaconda3/bin/python",
    "cpu_count": 4,
    "cpu_count_logical": 4,
    "cpu_freq": {
        "current": 2.8594999999999997,
        "min": 800.0,
        "max": 3600.0
    },
    "cpu_freq_per_core": [
        {
            "current": 2.865,
            "min": 800.0,
            "max": 3600.0
        },
        {
            "current": 3.219,
            "min": 800.0,
            "max": 3600.0
        },
        {
            "current": 2.468,
            "min": 800.0,
            "max": 3600.0
        },
        {
            "current": 2.886,
            "min": 800.0,
            "max": 3600.0
        }
    ],
    "disk": {
        "/": {
            "total": 109.88578796386719,
            "used": 8.077507019042969
        }
    },
    "memory": {
        "total": 15.489360809326172
    }
}
